pyntruprime/__init__.py
pyntruprime-0.0.3.dist-info/LICENSE
pyntruprime-0.0.3.dist-info/WHEEL
pyntruprime-0.0.3.dist-info/METADATA
pyntruprime-0.0.3.dist-info/RECORD
