Metadata-Version: 2.3
Name: pyntruprime
Version: 0.0.3
Summary: A Python wrapper for the libntruprime microlibrary
Keywords: post-quantum,cryptography,Streamlined NTRU Prime,libntruprime,pyntruprime
Author-email: Jonathan Levin <pyntruprime@riseup.net>
Requires-Python: >=3.6
Classifier: Development Status :: 3 - Alpha
Classifier: Topic :: Security :: Cryptography
Classifier: Topic :: Security
Project-URL: Source, https://www.github.com/ondesmartenot/pyntruprime
